{"_wandb":{"runtime":623},"train/loss":493.98785,"global_step":501760,"rollout/ep_len_mean":17925.385,"cumulative/total_episodes":26,"episode/mean_portfolio_100":1000,"episode/length":46254,"final/total_episodes":26,"train/learning_rate":0.0005,"final/max_drawdown_pct":0,"episode/total_return_pct":0,"charts/sharpe_aggressive_summary":{"size":48903,"path":"media/images/charts/sharpe_aggressive_summary_5044_64fc3f05c1abfc1543bf.png","format":"png","width":1400,"height":500,"_type":"image-file","sha256":"64fc3f05c1abfc1543bfe4f208c6b8aaec8dd052d90e5152fbbc204e93b160a4"},"final/max_portfolio":1000,"final/total_return_pct":0,"cumulative/worst_portfolio":1000,"train/policy_gradient_loss":-0.0010917113,"train/explained_variance":0.2669286,"train/clip_range":0.2,"episode/portfolio_value":1000,"train/entropy_loss":0.09714483,"rollout/ep_rew_mean":-12657.105,"train/approx_kl":0.008179414,"episode/mean_reward_100":-12657.10556292308,"cumulative/avg_episode_length":17925.384615384617,"_runtime":623,"episode/mean_return_100":0,"final/portfolio_value":1000,"episode/num_episodes":26,"train/clip_fraction":0.09375,"_step":8207,"episode/volatility_pct":0,"final/mean_return_pct":0,"episode/sharpe_ratio":0,"_timestamp":1.766433427586812e+09,"train/std":0.21963495,"cumulative/best_portfolio":1000,"final/mean_reward":-12657.10556292308,"time/fps":806,"final/mean_portfolio":1000,"train/value_loss":1014.41724,"timesteps":501700,"episode/reward":-1828.857206,"episode/max_drawdown_pct":0}